Metadata-Version: 1.0
Name: canonicalwebteam.gsa
Version: 2.0.1
Summary: A client for communicating with the Google Search Appliance.
Home-page: https://github.com/canonicalwebteam/gsa
Author: Canonical webteam
Author-email: robin+pypi@canonical.com
License: UNKNOWN
Platform: UNKNOWN
